{
  "footer-layout.mobile#mobile__footer--mainContainer": {
    "title": "footer__mobile--container",
    "props": {
      "blockClass": "mobile__footer--mainContainer",
      "children": [
        "flex-layout.row#footer__mobile--titles"
      ]
    }
  },

  "flex-layout.row#footer__mobile--titles": {
    "title": "footer titles",
    "props": {
      "blockClass": "footer__mobile--titles"
    },
    "children": [
      "social-networks#mobile"
    ]
  },
  "social-networks#mobile": {
    "props": {
      "socialNetworks": [
        {
          "url": "https://facebook.com/foo",
          "name": "Facebook"
        },
        {
          "url": "https://twitter.com/foo",
          "name": "Twitter"
        }
      ]
    }
  }
}
